evenger/__init__.py
evenger/evenger.py
evenger-2023.1.16.dist-info/LICENSE
evenger-2023.1.16.dist-info/METADATA
evenger-2023.1.16.dist-info/WHEEL
evenger-2023.1.16.dist-info/entry_points.txt
evenger-2023.1.16.dist-info/top_level.txt
evenger-2023.1.16.dist-info/RECORD
