Metadata-Version: 2.1
Name: evenger
Version: 2023.1.16
Summary: Create EVE-NG network topology with EVE-NG API and excel file
Author: Umur Arslan
License: MIT License
Project-URL: Homepage, https://github.com/umurarslan/evenger
Classifier: Programming Language :: Python :: 3
Classifier: License :: OSI Approved :: MIT License
Classifier: Operating System :: OS Independent
Requires-Python: >=3.9
License-File: LICENSE
Requires-Dist: pandas (>=1.5.2)
Requires-Dist: openpyxl (>=3.0.7)
Requires-Dist: requests (>=2.26.0)
Requires-Dist: Jinja2 (>=3.0.1)
